Magic Number:		0xcafebabe
Minor Version:		0
Major Version:		46 [1.2]
Constant Pool Count:	34
Access flags:		0x0020 [super ]
This class:		cp_info #8 <Teste>
Super class:		cp_info #9 <java/lang/Object>
Interfaces Count:	0
Fields Count:		0
Methods Count:		3
Attributes Count:	1

+Constant Pool:

[01]CONSTANT_Methodref:		Class name:	cp_info #9 <java/lang/Object>
				Name and type:	cp_info #20 <<init>()V>

[02]CONSTANT_Float		Bytes:	0x42c80000
				Float:	100.0000

[03]CONSTANT_Double		High bytes:		0x408f4000
				Low bytes:		0x00000000
				Double:			1000.000000

[04](large numeric continued)

[05]CONSTANT_Methodref:		Class name:	cp_info #8 <Teste>
				Name and type:	cp_info #21 <soma(II)I>

[06]CONSTANT_Fieldref:		Class name:	cp_info #22 <java/lang/System>
				Name and type:	cp_info #23 <outLjava/io/PrintStream;>

[07]CONSTANT_Methodref:		Class name:	cp_info #24 <java/io/PrintStream>
				Name and type:	cp_info #25 <print(I)V>

[08]CONSTANT_Class:		Class Name:	cp_info #26 <Teste>

[09]CONSTANT_Class:		Class Name:	cp_info #27 <java/lang/Object>

[10]CONSTANT_Utf8		Length of byte array:	6
				Length of string:	6
				String:			<init>

[11]CONSTANT_Utf8		Length of byte array:	3
				Length of string:	3
				String:			()V

[12]CONSTANT_Utf8		Length of byte array:	4
				Length of string:	4
				String:			Code

[13]CONSTANT_Utf8		Length of byte array:	15
				Length of string:	15
				String:			LineNumberTable

[14]CONSTANT_Utf8		Length of byte array:	4
				Length of string:	4
				String:			soma

[15]CONSTANT_Utf8		Length of byte array:	5
				Length of string:	5
				String:			(II)I

[16]CONSTANT_Utf8		Length of byte array:	4
				Length of string:	4
				String:			main

[17]CONSTANT_Utf8		Length of byte array:	22
				Length of string:	22
				String:			([Ljava/lang/String;)V

[18]CONSTANT_Utf8		Length of byte array:	10
				Length of string:	10
				String:			SourceFile

[19]CONSTANT_Utf8		Length of byte array:	10
				Length of string:	10
				String:			Teste.java

[20]CONSTANT_NameAndType	Name:		cp_info #10 <<init>>
				Descriptor:	cp_info #11 <()V>

[21]CONSTANT_NameAndType	Name:		cp_info #14 <soma>
				Descriptor:	cp_info #15 <(II)I>

[22]CONSTANT_Class:		Class Name:	cp_info #28 <java/lang/System>

[23]CONSTANT_NameAndType	Name:		cp_info #29 <out>
				Descriptor:	cp_info #30 <Ljava/io/PrintStream;>

[24]CONSTANT_Class:		Class Name:	cp_info #31 <java/io/PrintStream>

[25]CONSTANT_NameAndType	Name:		cp_info #32 <print>
				Descriptor:	cp_info #33 <(I)V>

[26]CONSTANT_Utf8		Length of byte array:	5
				Length of string:	5
				String:			Teste

[27]CONSTANT_Utf8		Length of byte array:	16
				Length of string:	16
				String:			java/lang/Object

[28]CONSTANT_Utf8		Length of byte array:	16
				Length of string:	16
				String:			java/lang/System

[29]CONSTANT_Utf8		Length of byte array:	3
				Length of string:	3
				String:			out

[30]CONSTANT_Utf8		Length of byte array:	21
				Length of string:	21
				String:			Ljava/io/PrintStream;

[31]CONSTANT_Utf8		Length of byte array:	19
				Length of string:	19
				String:			java/io/PrintStream

[32]CONSTANT_Utf8		Length of byte array:	5
				Length of string:	5
				String:			print

[33]CONSTANT_Utf8		Length of byte array:	4
				Length of string:	4
				String:			(I)V

+Interfaces

+Fields
	Member Count:		0

+Methods
	Member Count:		3

	[0] <init>
		Name:			cp_info #10 <<init>>
		Descriptor:		cp_info #11 <()V>
		Access flags:		0x0000 []

		[0] Code
			Attribute name index:		cp_info #12
			Attribute length:		29
		Bytecode:
		-------------------------------------------
			 0  aload_0
			 1  invokespecial 1 <java/lang/Object.<init>>
			 4  return
		-------------------------------------------

		Exception table:
	----------------------------------------------------------------------
	Nr.  |  start_pc  |  end_pc  |  handler_pc  |  catch_type  |  verbose
	----------------------------------------------------------------------

		Misc:
		Maximum stack depth:		1
		Maximum local variables:	1
		Code length:			5

		[0] LineNumberTable
			Attribute name index:		cp_info #13
			Attribute length:		6
			Nr.	    start_pc	    line_number
		-------------------------------------------------
			0		0		1
		-------------------------------------------------

	[1] soma
		Name:			cp_info #14 <soma>
		Descriptor:		cp_info #15 <(II)I>
		Access flags:		0x0009 [static public ]

		[0] Code
			Attribute name index:		cp_info #12
			Attribute length:		28
		Bytecode:
		-------------------------------------------
			 0  iload_0
			 1  iload_1
			 2  iadd
			 3  ireturn
		-------------------------------------------

		Exception table:
	----------------------------------------------------------------------
	Nr.  |  start_pc  |  end_pc  |  handler_pc  |  catch_type  |  verbose
	----------------------------------------------------------------------

		Misc:
		Maximum stack depth:		2
		Maximum local variables:	2
		Code length:			4

		[0] LineNumberTable
			Attribute name index:		cp_info #13
			Attribute length:		6
			Nr.	    start_pc	    line_number
		-------------------------------------------------
			0		0		3
		-------------------------------------------------

	[2] main
		Name:			cp_info #16 <main>
		Descriptor:		cp_info #17 <([Ljava/lang/String;)V>
		Access flags:		0x0009 [static public ]

		[0] Code
			Attribute name index:		cp_info #12
			Attribute length:		95
		Bytecode:
		-------------------------------------------
			 0  ldc 2
			 2  fstore_2
			 3  ldc2_w 0 3
			 6  dstore_3
			 7  bipush 20
			 9  istore 5
			11  iconst_0
			12  istore_1
			13  iload_1
			14  bipush 10
			16  if_icmpge 0 18
			19  iload 5
			21  bipush 10
			23  invokestatic 5 <Teste.soma>
			26  istore 5
			28  iinc 1 1
			31  goto 255 238
			34  getstatic 0 6
			37  iload 5
			39  invokevirtual 7 <java/io/PrintStream.print>
			42  return
		-------------------------------------------

		Exception table:
	----------------------------------------------------------------------
	Nr.  |  start_pc  |  end_pc  |  handler_pc  |  catch_type  |  verbose
	----------------------------------------------------------------------

		Misc:
		Maximum stack depth:		2
		Maximum local variables:	6
		Code length:			43

		[0] LineNumberTable
			Attribute name index:		cp_info #13
			Attribute length:		34
			Nr.	    start_pc	    line_number
		-------------------------------------------------
			0		0		7
			1		3		8
			2		7		9
			3		11		10
			4		19		11
			5		28		10
			6		34		13
			7		42		14
		-------------------------------------------------

+Attributes

		[0] SourceFile
			Attribute name index:		cp_info #18
			Attribute length:		2
			Source file name index:		cp_info #19 <Teste.java>
