Magic Number:		0xcafebabe
Minor Version:		0
Major Version:		46 [1.2]
Constant Pool Count:	42
Access flags:		0x0020 [super ]
This class:		cp_info #12 <TesteInvoke>
Super class:		cp_info #13 <java/lang/Object>
Interfaces Count:	0
Fields Count:		1
Methods Count:		2
Attributes Count:	1

+Constant Pool:

[01]CONSTANT_Methodref:		Class name:	cp_info #13 <java/lang/Object>
				Name and type:	cp_info #24 <<init>()V>

[02]CONSTANT_Long		HIGH_BYTES:		0x00000000
				LOW_BYTES:		0x03e8
				Long:			1000

[03](large numeric continued)

[04]CONSTANT_Class:		Class Name:	cp_info #25 <SomaLong>

[05]CONSTANT_Methodref:		Class name:	cp_info #4 <SomaLong>
				Name and type:	cp_info #24 <<init>()V>

[06]CONSTANT_Fieldref:		Class name:	cp_info #12 <TesteInvoke>
				Name and type:	cp_info #26 <somaLongLSomaLong;>

[07]CONSTANT_Long		HIGH_BYTES:		0x00000000
				LOW_BYTES:		0x01f4
				Long:			500

[08](large numeric continued)

[09]CONSTANT_Methodref:		Class name:	cp_info #4 <SomaLong>
				Name and type:	cp_info #27 <soma(JJ)J>

[10]CONSTANT_Fieldref:		Class name:	cp_info #28 <java/lang/System>
				Name and type:	cp_info #29 <outLjava/io/PrintStream;>

[11]CONSTANT_Methodref:		Class name:	cp_info #30 <java/io/PrintStream>
				Name and type:	cp_info #31 <println(J)V>

[12]CONSTANT_Class:		Class Name:	cp_info #32 <TesteInvoke>

[13]CONSTANT_Class:		Class Name:	cp_info #33 <java/lang/Object>

[14]CONSTANT_Utf8		Length of byte array:	8
				Length of string:	8
				String:			somaLong

[15]CONSTANT_Utf8		Length of byte array:	10
				Length of string:	10
				String:			LSomaLong;

[16]CONSTANT_Utf8		Length of byte array:	6
				Length of string:	6
				String:			<init>

[17]CONSTANT_Utf8		Length of byte array:	3
				Length of string:	3
				String:			()V

[18]CONSTANT_Utf8		Length of byte array:	4
				Length of string:	4
				String:			Code

[19]CONSTANT_Utf8		Length of byte array:	15
				Length of string:	15
				String:			LineNumberTable

[20]CONSTANT_Utf8		Length of byte array:	4
				Length of string:	4
				String:			main

[21]CONSTANT_Utf8		Length of byte array:	22
				Length of string:	22
				String:			([Ljava/lang/String;)V

[22]CONSTANT_Utf8		Length of byte array:	10
				Length of string:	10
				String:			SourceFile

[23]CONSTANT_Utf8		Length of byte array:	16
				Length of string:	16
				String:			TesteInvoke.java

[24]CONSTANT_NameAndType	Name:		cp_info #16 <<init>>
				Descriptor:	cp_info #17 <()V>

[25]CONSTANT_Utf8		Length of byte array:	8
				Length of string:	8
				String:			SomaLong

[26]CONSTANT_NameAndType	Name:		cp_info #14 <somaLong>
				Descriptor:	cp_info #15 <LSomaLong;>

[27]CONSTANT_NameAndType	Name:		cp_info #34 <soma>
				Descriptor:	cp_info #35 <(JJ)J>

[28]CONSTANT_Class:		Class Name:	cp_info #36 <java/lang/System>

[29]CONSTANT_NameAndType	Name:		cp_info #37 <out>
				Descriptor:	cp_info #38 <Ljava/io/PrintStream;>

[30]CONSTANT_Class:		Class Name:	cp_info #39 <java/io/PrintStream>

[31]CONSTANT_NameAndType	Name:		cp_info #40 <println>
				Descriptor:	cp_info #41 <(J)V>

[32]CONSTANT_Utf8		Length of byte array:	11
				Length of string:	11
				String:			TesteInvoke

[33]CONSTANT_Utf8		Length of byte array:	16
				Length of string:	16
				String:			java/lang/Object

[34]CONSTANT_Utf8		Length of byte array:	4
				Length of string:	4
				String:			soma

[35]CONSTANT_Utf8		Length of byte array:	5
				Length of string:	5
				String:			(JJ)J

[36]CONSTANT_Utf8		Length of byte array:	16
				Length of string:	16
				String:			java/lang/System

[37]CONSTANT_Utf8		Length of byte array:	3
				Length of string:	3
				String:			out

[38]CONSTANT_Utf8		Length of byte array:	21
				Length of string:	21
				String:			Ljava/io/PrintStream;

[39]CONSTANT_Utf8		Length of byte array:	19
				Length of string:	19
				String:			java/io/PrintStream

[40]CONSTANT_Utf8		Length of byte array:	7
				Length of string:	7
				String:			println

[41]CONSTANT_Utf8		Length of byte array:	4
				Length of string:	4
				String:			(J)V

+Interfaces

+Fields
	Member Count:		1

	[0] somaLong	Name:				cp_info #14 <somaLong>
			Descriptor:			cp_info #15 <LSomaLong;>
			Access flags:			0x000a [static private ]

+Methods
	Member Count:		2

	[0] <init>
		Name:			cp_info #16 <<init>>
		Descriptor:		cp_info #17 <()V>
		Access flags:		0x0000 []

		[0] Code
			Attribute name index:		cp_info #18
			Attribute length:		29
		Bytecode:
		-------------------------------------------
			 0  aload_0
			 1  invokespecial 1 <java/lang/Object.<init>>
			 4  return
		-------------------------------------------

		Exception table:
	----------------------------------------------------------------------
	Nr.  |  start_pc  |  end_pc  |  handler_pc  |  catch_type  |  verbose
	----------------------------------------------------------------------

		Misc:
		Maximum stack depth:		1
		Maximum local variables:	1
		Code length:			5

		[0] LineNumberTable
			Attribute name index:		cp_info #19
			Attribute length:		6
			Nr.	    start_pc	    line_number
		-------------------------------------------------
			0		0		2
		-------------------------------------------------

	[1] main
		Name:			cp_info #20 <main>
		Descriptor:		cp_info #21 <([Ljava/lang/String;)V>
		Access flags:		0x0009 [static public ]

		[0] Code
			Attribute name index:		cp_info #18
			Attribute length:		74
		Bytecode:
		-------------------------------------------
			 0  ldc2_w 0 2
			 3  lstore_1
			 4  new 0 4
			 7  dup
			 8  invokespecial 5 <SomaLong.<init>>
			11  putstatic 0 6
			14  getstatic 0 6
			17  pop
			18  lload_1
			19  ldc2_w 0 7
			22  invokestatic 9 <SomaLong.soma>
			25  lstore_1
			26  getstatic 0 10
			29  lload_1
			30  invokevirtual 11 <java/io/PrintStream.println>
			33  return
		-------------------------------------------

		Exception table:
	----------------------------------------------------------------------
	Nr.  |  start_pc  |  end_pc  |  handler_pc  |  catch_type  |  verbose
	----------------------------------------------------------------------

		Misc:
		Maximum stack depth:		4
		Maximum local variables:	3
		Code length:			34

		[0] LineNumberTable
			Attribute name index:		cp_info #19
			Attribute length:		22
			Nr.	    start_pc	    line_number
		-------------------------------------------------
			0		0		5
			1		4		7
			2		14		8
			3		26		10
			4		33		11
		-------------------------------------------------

+Attributes

		[0] SourceFile
			Attribute name index:		cp_info #22
			Attribute length:		2
			Source file name index:		cp_info #23 <TesteInvoke.java>
