Magic Number:		0xcafebabe
Minor Version:		0
Major Version:		46 [1.2]
Constant Pool Count:	71
Access flags:		0x0020 [super ]
This class:		cp_info #1 <testeStatic>
Super class:		cp_info #3 <java/lang/Object>
Interfaces Count:	0
Fields Count:		5
Methods Count:		4
Attributes Count:	1

+Constant Pool:

[01]CONSTANT_Class:		Class Name:	cp_info #2 <testeStatic>

[02]CONSTANT_Utf8		Length of byte array:	11
				Length of string:	11
				String:			testeStatic

[03]CONSTANT_Class:		Class Name:	cp_info #4 <java/lang/Object>

[04]CONSTANT_Utf8		Length of byte array:	16
				Length of string:	16
				String:			java/lang/Object

[05]CONSTANT_Utf8		Length of byte array:	6
				Length of string:	6
				String:			number

[06]CONSTANT_Utf8		Length of byte array:	1
				Length of string:	1
				String:			I

[07]CONSTANT_Utf8		Length of byte array:	4
				Length of string:	4
				String:			nome

[08]CONSTANT_Utf8		Length of byte array:	18
				Length of string:	18
				String:			Ljava/lang/String;

[09]CONSTANT_Utf8		Length of byte array:	2
				Length of string:	2
				String:			td

[10]CONSTANT_Utf8		Length of byte array:	1
				Length of string:	1
				String:			D

[11]CONSTANT_Utf8		Length of byte array:	2
				Length of string:	2
				String:			tl

[12]CONSTANT_Utf8		Length of byte array:	1
				Length of string:	1
				String:			J

[13]CONSTANT_Utf8		Length of byte array:	2
				Length of string:	2
				String:			tf

[14]CONSTANT_Utf8		Length of byte array:	1
				Length of string:	1
				String:			F

[15]CONSTANT_Utf8		Length of byte array:	8
				Length of string:	8
				String:			<clinit>

[16]CONSTANT_Utf8		Length of byte array:	3
				Length of string:	3
				String:			()V

[17]CONSTANT_Utf8		Length of byte array:	4
				Length of string:	4
				String:			Code

[18]CONSTANT_Fieldref:		Class name:	cp_info #1 <testeStatic>
				Name and type:	cp_info #19 <numberI>

[19]CONSTANT_NameAndType	Name:		cp_info #5 <number>
				Descriptor:	cp_info #6 <I>

[20]CONSTANT_String		String:		cp_info #21 <Teste>

[21]CONSTANT_Utf8		Length of byte array:	5
				Length of string:	5
				String:			Teste

[22]CONSTANT_Fieldref:		Class name:	cp_info #1 <testeStatic>
				Name and type:	cp_info #23 <nomeLjava/lang/String;>

[23]CONSTANT_NameAndType	Name:		cp_info #7 <nome>
				Descriptor:	cp_info #8 <Ljava/lang/String;>

[24]CONSTANT_Double		High bytes:		0x400d70a3
				Low bytes:		0xd70a3d71
				Double:			nan

[25](large numeric continued)

[26]CONSTANT_Fieldref:		Class name:	cp_info #1 <testeStatic>
				Name and type:	cp_info #27 <tdD>

[27]CONSTANT_NameAndType	Name:		cp_info #9 <td>
				Descriptor:	cp_info #10 <D>

[28]CONSTANT_Long		HIGH_BYTES:		0x00000000
				LOW_BYTES:		0x0003
				Long:			3

[29](large numeric continued)

[30]CONSTANT_Fieldref:		Class name:	cp_info #1 <testeStatic>
				Name and type:	cp_info #31 <tlJ>

[31]CONSTANT_NameAndType	Name:		cp_info #11 <tl>
				Descriptor:	cp_info #12 <J>

[32]CONSTANT_Float		Bytes:	0x40b9999a
				Float:	5.8000

[33]CONSTANT_Fieldref:		Class name:	cp_info #1 <testeStatic>
				Name and type:	cp_info #34 <tfF>

[34]CONSTANT_NameAndType	Name:		cp_info #13 <tf>
				Descriptor:	cp_info #14 <F>

[35]CONSTANT_Utf8		Length of byte array:	15
				Length of string:	15
				String:			LineNumberTable

[36]CONSTANT_Utf8		Length of byte array:	6
				Length of string:	6
				String:			<init>

[37]CONSTANT_Methodref:		Class name:	cp_info #3 <java/lang/Object>
				Name and type:	cp_info #38 <<init>()V>

[38]CONSTANT_NameAndType	Name:		cp_info #36 <<init>>
				Descriptor:	cp_info #16 <()V>

[39]CONSTANT_Utf8		Length of byte array:	8
				Length of string:	8
				String:			funfloat

[40]CONSTANT_Utf8		Length of byte array:	5
				Length of string:	5
				String:			(FF)F

[41]CONSTANT_Utf8		Length of byte array:	4
				Length of string:	4
				String:			main

[42]CONSTANT_Utf8		Length of byte array:	22
				Length of string:	22
				String:			([Ljava/lang/String;)V

[43]CONSTANT_Fieldref:		Class name:	cp_info #44 <java/lang/System>
				Name and type:	cp_info #46 <outLjava/io/PrintStream;>

[44]CONSTANT_Class:		Class Name:	cp_info #45 <java/lang/System>

[45]CONSTANT_Utf8		Length of byte array:	16
				Length of string:	16
				String:			java/lang/System

[46]CONSTANT_NameAndType	Name:		cp_info #47 <out>
				Descriptor:	cp_info #48 <Ljava/io/PrintStream;>

[47]CONSTANT_Utf8		Length of byte array:	3
				Length of string:	3
				String:			out

[48]CONSTANT_Utf8		Length of byte array:	21
				Length of string:	21
				String:			Ljava/io/PrintStream;

[49]CONSTANT_Methodref:		Class name:	cp_info #50 <java/io/PrintStream>
				Name and type:	cp_info #52 <println(I)V>

[50]CONSTANT_Class:		Class Name:	cp_info #51 <java/io/PrintStream>

[51]CONSTANT_Utf8		Length of byte array:	19
				Length of string:	19
				String:			java/io/PrintStream

[52]CONSTANT_NameAndType	Name:		cp_info #53 <println>
				Descriptor:	cp_info #54 <(I)V>

[53]CONSTANT_Utf8		Length of byte array:	7
				Length of string:	7
				String:			println

[54]CONSTANT_Utf8		Length of byte array:	4
				Length of string:	4
				String:			(I)V

[55]CONSTANT_Methodref:		Class name:	cp_info #50 <java/io/PrintStream>
				Name and type:	cp_info #56 <println(Ljava/lang/String;)V>

[56]CONSTANT_NameAndType	Name:		cp_info #53 <println>
				Descriptor:	cp_info #57 <(Ljava/lang/String;)V>

[57]CONSTANT_Utf8		Length of byte array:	21
				Length of string:	21
				String:			(Ljava/lang/String;)V

[58]CONSTANT_Methodref:		Class name:	cp_info #50 <java/io/PrintStream>
				Name and type:	cp_info #59 <println(D)V>

[59]CONSTANT_NameAndType	Name:		cp_info #53 <println>
				Descriptor:	cp_info #60 <(D)V>

[60]CONSTANT_Utf8		Length of byte array:	4
				Length of string:	4
				String:			(D)V

[61]CONSTANT_Methodref:		Class name:	cp_info #50 <java/io/PrintStream>
				Name and type:	cp_info #62 <println(J)V>

[62]CONSTANT_NameAndType	Name:		cp_info #53 <println>
				Descriptor:	cp_info #63 <(J)V>

[63]CONSTANT_Utf8		Length of byte array:	4
				Length of string:	4
				String:			(J)V

[64]CONSTANT_Methodref:		Class name:	cp_info #50 <java/io/PrintStream>
				Name and type:	cp_info #65 <println(F)V>

[65]CONSTANT_NameAndType	Name:		cp_info #53 <println>
				Descriptor:	cp_info #66 <(F)V>

[66]CONSTANT_Utf8		Length of byte array:	4
				Length of string:	4
				String:			(F)V

[67]CONSTANT_Methodref:		Class name:	cp_info #1 <testeStatic>
				Name and type:	cp_info #68 <funfloat(FF)F>

[68]CONSTANT_NameAndType	Name:		cp_info #39 <funfloat>
				Descriptor:	cp_info #40 <(FF)F>

[69]CONSTANT_Utf8		Length of byte array:	10
				Length of string:	10
				String:			SourceFile

[70]CONSTANT_Utf8		Length of byte array:	16
				Length of string:	16
				String:			testeStatic.java

+Interfaces

+Fields
	Member Count:		5

	[0] number	Name:				cp_info #5 <number>
			Descriptor:			cp_info #6 <I>
			Access flags:			0x000a [static private ]

	[1] nome	Name:				cp_info #7 <nome>
			Descriptor:			cp_info #8 <Ljava/lang/String;>
			Access flags:			0x000a [static private ]

	[2] td	Name:				cp_info #9 <td>
			Descriptor:			cp_info #10 <D>
			Access flags:			0x000a [static private ]

	[3] tl	Name:				cp_info #11 <tl>
			Descriptor:			cp_info #12 <J>
			Access flags:			0x000a [static private ]

	[4] tf	Name:				cp_info #13 <tf>
			Descriptor:			cp_info #14 <F>
			Access flags:			0x000a [static private ]

+Methods
	Member Count:		4

	[0] <clinit>
		Name:			cp_info #15 <<clinit>>
		Descriptor:		cp_info #16 <()V>
		Access flags:		0x0008 [static ]

		[0] Code
			Attribute name index:		cp_info #17
			Attribute length:		72
		Bytecode:
		-------------------------------------------
			 0  bipush 22
			 2  putstatic 0 18
			 5  ldc 20
			 7  putstatic 0 22
			10  ldc2_w 0 24
			13  putstatic 0 26
			16  ldc2_w 0 28
			19  putstatic 0 30
			22  ldc 32
			24  putstatic 0 33
			27  return
		-------------------------------------------

		Exception table:
	----------------------------------------------------------------------
	Nr.  |  start_pc  |  end_pc  |  handler_pc  |  catch_type  |  verbose
	----------------------------------------------------------------------

		Misc:
		Maximum stack depth:		2
		Maximum local variables:	0
		Code length:			28

		[0] LineNumberTable
			Attribute name index:		cp_info #35
			Attribute length:		26
			Nr.	    start_pc	    line_number
		-------------------------------------------------
			0		0		2
			1		5		3
			2		10		4
			3		16		5
			4		22		6
			5		27		1
		-------------------------------------------------

	[1] <init>
		Name:			cp_info #36 <<init>>
		Descriptor:		cp_info #16 <()V>
		Access flags:		0x0000 []

		[0] Code
			Attribute name index:		cp_info #17
			Attribute length:		29
		Bytecode:
		-------------------------------------------
			 0  aload_0
			 1  invokespecial 37 <java/lang/Object.<init>>
			 4  return
		-------------------------------------------

		Exception table:
	----------------------------------------------------------------------
	Nr.  |  start_pc  |  end_pc  |  handler_pc  |  catch_type  |  verbose
	----------------------------------------------------------------------

		Misc:
		Maximum stack depth:		1
		Maximum local variables:	1
		Code length:			5

		[0] LineNumberTable
			Attribute name index:		cp_info #35
			Attribute length:		6
			Nr.	    start_pc	    line_number
		-------------------------------------------------
			0		0		1
		-------------------------------------------------

	[2] funfloat
		Name:			cp_info #39 <funfloat>
		Descriptor:		cp_info #40 <(FF)F>
		Access flags:		0x000a [static private ]

		[0] Code
			Attribute name index:		cp_info #17
			Attribute length:		28
		Bytecode:
		-------------------------------------------
			 0  fload_0
			 1  fload_1
			 2  fmul
			 3  freturn
		-------------------------------------------

		Exception table:
	----------------------------------------------------------------------
	Nr.  |  start_pc  |  end_pc  |  handler_pc  |  catch_type  |  verbose
	----------------------------------------------------------------------

		Misc:
		Maximum stack depth:		2
		Maximum local variables:	2
		Code length:			4

		[0] LineNumberTable
			Attribute name index:		cp_info #35
			Attribute length:		6
			Nr.	    start_pc	    line_number
		-------------------------------------------------
			0		0		9
		-------------------------------------------------

	[3] main
		Name:			cp_info #41 <main>
		Descriptor:		cp_info #42 <([Ljava/lang/String;)V>
		Access flags:		0x0009 [static public ]

		[0] Code
			Attribute name index:		cp_info #17
			Attribute length:		109
		Bytecode:
		-------------------------------------------
			 0  getstatic 0 43
			 3  getstatic 0 18
			 6  invokevirtual 49 <java/io/PrintStream.println>
			 9  getstatic 0 43
			12  getstatic 0 22
			15  invokevirtual 55 <java/io/PrintStream.println>
			18  getstatic 0 43
			21  getstatic 0 26
			24  invokevirtual 58 <java/io/PrintStream.println>
			27  getstatic 0 43
			30  getstatic 0 30
			33  invokevirtual 61 <java/io/PrintStream.println>
			36  getstatic 0 43
			39  getstatic 0 33
			42  invokevirtual 64 <java/io/PrintStream.println>
			45  getstatic 0 43
			48  getstatic 0 33
			51  getstatic 0 33
			54  invokestatic 67 <testeStatic.funfloat>
			57  invokevirtual 64 <java/io/PrintStream.println>
			60  return
		-------------------------------------------

		Exception table:
	----------------------------------------------------------------------
	Nr.  |  start_pc  |  end_pc  |  handler_pc  |  catch_type  |  verbose
	----------------------------------------------------------------------

		Misc:
		Maximum stack depth:		3
		Maximum local variables:	1
		Code length:			61

		[0] LineNumberTable
			Attribute name index:		cp_info #35
			Attribute length:		30
			Nr.	    start_pc	    line_number
		-------------------------------------------------
			0		0		12
			1		9		13
			2		18		14
			3		27		15
			4		36		16
			5		45		17
			6		60		18
		-------------------------------------------------

+Attributes

		[0] SourceFile
			Attribute name index:		cp_info #69
			Attribute length:		2
			Source file name index:		cp_info #70 <testeStatic.java>
